passagemath_primesieve_primecount.libs/libgcc_s-e1925712.so.1
passagemath_primesieve_primecount.libs/libgomp-6d7f45f1.so.1.0.0
passagemath_primesieve_primecount.libs/libprimecount-262a343c.so.7.19
passagemath_primesieve_primecount.libs/libprimesieve-6ab773da.so.12.9.0
passagemath_primesieve_primecount.libs/libstdc++-b2d5af4b.so.6.0.33
primecountpy/__init__.py
primecountpy/defs.pxd
primecountpy/primecount.cpp
primecountpy/primecount.cpython-312-i386-linux-musl.so
primecountpy/primecount.pyx
passagemath_primesieve_primecount-0.1.1.2.dist-info/METADATA
passagemath_primesieve_primecount-0.1.1.2.dist-info/WHEEL
passagemath_primesieve_primecount-0.1.1.2.dist-info/top_level.txt
passagemath_primesieve_primecount-0.1.1.2.dist-info/RECORD
passagemath_primesieve_primecount-0.1.1.2.dist-info/licenses/AUTHORS
passagemath_primesieve_primecount-0.1.1.2.dist-info/licenses/LICENSE
