Metadata-Version: 2.4
Name: passagemath-primesieve-primecount
Version: 0.1.1.2
Summary: Cython interface for the primecount library
Author-email: SageMath Developers <sage-devel@googlegroups.com>
Maintainer: Matthias Köppe, passagemath contributors
License:                     GNU GENERAL PUBLIC LICENSE
Project-URL: Repo (upstream), https://github.com/dimpase/primecountpy
Project-URL: Repo, https://github.com/passagemath/passagemath-primesieve-primecount
Project-URL: User Manual, https://primecountpy.readthedocs.io
Project-URL: Bug Tracker (upstream), https://github.com/dimpase/primecountpy/issues
Project-URL: Bug Tracker, https://github.com/passagemath/passagemath-primesieve-primecount/issues
Classifier: Development Status :: 5 - Production/Stable
Classifier: Intended Audience :: Science/Research
Classifier: Programming Language :: Python :: 3
Classifier: Topic :: Scientific/Engineering :: Mathematics
Requires-Python: >=3.9
License-File: LICENSE
License-File: AUTHORS
Requires-Dist: cysignals
Dynamic: license-file
